coopr.neos-1.1.2-py2.7-nspkg.pth
coopr/neos/__init__.py
coopr/neos/kestrel.py
coopr/neos/plugins/__init__.py
coopr/neos/plugins/kestrel_plugin.py
coopr/neos/plugins/NEOS.py
coopr.neos-1.1.2.dist-info/DESCRIPTION.rst
coopr.neos-1.1.2.dist-info/METADATA
coopr.neos-1.1.2.dist-info/metadata.json
coopr.neos-1.1.2.dist-info/namespace_packages.txt
coopr.neos-1.1.2.dist-info/RECORD
coopr.neos-1.1.2.dist-info/top_level.txt
coopr.neos-1.1.2.dist-info/WHEEL
